CHANGES.rst
MANIFEST.in
README.rst
requirements.txt
setup.cfg
setup.py
cs/__init__.py
cs.pfg.mipago.egg-info/PKG-INFO
cs.pfg.mipago.egg-info/SOURCES.txt
cs.pfg.mipago.egg-info/dependency_links.txt
cs.pfg.mipago.egg-info/entry_points.txt
cs.pfg.mipago.egg-info/namespace_packages.txt
cs.pfg.mipago.egg-info/not-zip-safe
cs.pfg.mipago.egg-info/requires.txt
cs.pfg.mipago.egg-info/top_level.txt
cs/pfg/__init__.py
cs/pfg/mipago/README.txt
cs/pfg/mipago/__init__.py
cs/pfg/mipago/config.py
cs/pfg/mipago/configure.zcml
cs/pfg/mipago/rebuild_i18n.sh
cs/pfg/mipago/testing.py
cs/pfg/mipago/browser/__init__.py
cs/pfg/mipago/browser/configure.zcml
cs/pfg/mipago/browser/confirmation.py
cs/pfg/mipago/browser/export.py
cs/pfg/mipago/browser/extra_template.pt
cs/pfg/mipago/browser/manage.pt
cs/pfg/mipago/browser/manage.py
cs/pfg/mipago/browser/payment.pt
cs/pfg/mipago/browser/payment.py
cs/pfg/mipago/browser/redirect.py
cs/pfg/mipago/content/__init__.py
cs/pfg/mipago/content/configure.zcml
cs/pfg/mipago/content/mipagoadapter.py
cs/pfg/mipago/interfaces/__init__.py
cs/pfg/mipago/interfaces/mipagoadapter.py
cs/pfg/mipago/locales/cs.pfg.mipago-manual.pot
cs/pfg/mipago/locales/cs.pfg.mipago.pot
cs/pfg/mipago/locales/plone.pot
cs/pfg/mipago/locales/es/LC_MESSAGES/cs.pfg.mipago.mo
cs/pfg/mipago/locales/es/LC_MESSAGES/cs.pfg.mipago.po
cs/pfg/mipago/locales/es/LC_MESSAGES/plone.mo
cs/pfg/mipago/locales/es/LC_MESSAGES/plone.po
cs/pfg/mipago/locales/eu/LC_MESSAGES/cs.pfg.mipago.mo
cs/pfg/mipago/locales/eu/LC_MESSAGES/cs.pfg.mipago.po
cs/pfg/mipago/locales/eu/LC_MESSAGES/plone.mo
cs/pfg/mipago/locales/eu/LC_MESSAGES/plone.po
cs/pfg/mipago/profiles/default/browserlayer.xml
cs/pfg/mipago/profiles/default/factorytool.xml
cs/pfg/mipago/profiles/default/metadata.xml
cs/pfg/mipago/profiles/default/rolemap.xml
cs/pfg/mipago/profiles/default/types.xml
cs/pfg/mipago/profiles/default/workflows.xml
cs/pfg/mipago/profiles/default/types/FormFolder.xml
cs/pfg/mipago/profiles/default/types/MiPagoAdapter.xml
cs/pfg/mipago/profiles/uninstall/browserlayer.xml
cs/pfg/mipago/tests/__init__.py
cs/pfg/mipago/tests/test_setup.py
docs/source/conf.py
docs/source/history.rst
docs/source/index.rst
docs/source/usage.rst