Metadata-Version: 2.1
Name: cs.pfg.mipago
Version: 1.0
Summary: PloneFormGen adapter to pay with Basque Government's payment service
Home-page: https://github.com/codesyntax/cs.pfg.mipago
Author: Mikel Larreategi
Author-email: mlarreategi@codesyntax.com
License: GPL
Platform: UNKNOWN
Classifier: Framework :: Plone
Classifier: Intended Audience :: Developers
Classifier: License :: OSI Approved :: GNU General Public License (GPL)
Provides-Extra: test
